MANIFEST.in
README.rst
setup.py
fh_drf_friendship.egg-info/PKG-INFO
fh_drf_friendship.egg-info/SOURCES.txt
fh_drf_friendship.egg-info/dependency_links.txt
fh_drf_friendship.egg-info/requires.txt
fh_drf_friendship.egg-info/top_level.txt
rest_framework_friendship/__init__.py
rest_framework_friendship/permissions.py
rest_framework_friendship/serializers.py
rest_framework_friendship/views.py