Metadata-Version: 1.0
Name: fh-drf-friendship
Version: 0.1.3
Summary: A library to provide ViewSets for django-friendship to use with Django Rest Framework projects.
Home-page: http://www.futurehaus.com/
Author: UNKNOWN
Author-email: UNKNOWN
License: UNKNOWN
Platform: UNKNOWN
